jupyterlab_toscmode/__init__.py
jupyterlab_toscmode/_version.py
jupyterlab_toscmode-0.2.0.data/data/share/jupyter/labextensions/jupyterlab_toscmode/package.json
jupyterlab_toscmode-0.2.0.data/data/share/jupyter/labextensions/jupyterlab_toscmode/schemas/jupyterlab_toscmode/package.json.orig
jupyterlab_toscmode-0.2.0.data/data/share/jupyter/labextensions/jupyterlab_toscmode/schemas/jupyterlab_toscmode/plugin.json
jupyterlab_toscmode-0.2.0.data/data/share/jupyter/labextensions/jupyterlab_toscmode/static/509.c57def9f40d7f5a492d4.js
jupyterlab_toscmode-0.2.0.data/data/share/jupyter/labextensions/jupyterlab_toscmode/static/728.d9d0cd6aac5b3d0dd3f7.js
jupyterlab_toscmode-0.2.0.data/data/share/jupyter/labextensions/jupyterlab_toscmode/static/remoteEntry.35274b237aec6f819749.js
jupyterlab_toscmode-0.2.0.data/data/share/jupyter/labextensions/jupyterlab_toscmode/static/style.js
jupyterlab_toscmode-0.2.0.data/data/share/jupyter/labextensions/jupyterlab_toscmode/static/third-party-licenses.json
jupyterlab_toscmode-0.2.0.data/data/share/jupyter/labextensions/jupyterlab_toscmode/install.json
jupyterlab_toscmode-0.2.0.dist-info/METADATA
jupyterlab_toscmode-0.2.0.dist-info/WHEEL
jupyterlab_toscmode-0.2.0.dist-info/licenses/LICENSE
jupyterlab_toscmode-0.2.0.dist-info/RECORD
