Metadata-Version: 2.3
Name: jupyterlab_toscmode
Version: 0.2.0
Summary: Adds a Showcase Mode to Jupyter Lab
Project-URL: Homepage, https://github.com/toscm/toscmode
Project-URL: Bug Tracker, https://github.com/toscm/toscmode/issues
Project-URL: Repository, https://github.com/toscm/toscmode.git
Author-email: Tobias Schmidt <tobias.schmidt331@gmail.com>
License: BSD 3-Clause License
License-File: LICENSE
Keywords: jupyter,jupyterlab,jupyterlab-extension
Classifier: Framework :: Jupyter
Classifier: Framework :: Jupyter :: JupyterLab
Classifier: Framework :: Jupyter :: JupyterLab :: 4
Classifier: Framework :: Jupyter :: JupyterLab :: Extensions
Classifier: Framework :: Jupyter :: JupyterLab :: Extensions :: Prebuilt
Classifier: License :: OSI Approved :: BSD License
Classifier: Programming Language :: Python
Classifier: Programming Language :: Python :: 3
Classifier: Programming Language :: Python :: 3.8
Classifier: Programming Language :: Python :: 3.9
Classifier: Programming Language :: Python :: 3.10
Classifier: Programming Language :: Python :: 3.11
Classifier: Programming Language :: Python :: 3.12
Requires-Python: >=3.8
